cdk_cloudformation_netapp_fsxn_volume/__init__.py
cdk_cloudformation_netapp_fsxn_volume/py.typed
cdk_cloudformation_netapp_fsxn_volume/_jsii/__init__.py
cdk_cloudformation_netapp_fsxn_volume/_jsii/netapp-fsxn-volume@1.0.0-alpha.7.jsii.tgz
cdk_cloudformation_netapp_fsxn_volume-1.0.0a7.dist-info/LICENSE
cdk_cloudformation_netapp_fsxn_volume-1.0.0a7.dist-info/METADATA
cdk_cloudformation_netapp_fsxn_volume-1.0.0a7.dist-info/WHEEL
cdk_cloudformation_netapp_fsxn_volume-1.0.0a7.dist-info/top_level.txt
cdk_cloudformation_netapp_fsxn_volume-1.0.0a7.dist-info/RECORD
