Metadata-Version: 2.2
Name: cdk-cloudformation-netapp-fsxn-volume
Version: 1.0.0a7
Summary: A volume is a logical storage unit which provides flexible space for data files, snapshots, and block devices. The NetApp:FSxN custom resource allows you to configure and manage FSX for ONTAP volumes by specifying parameters such as volume name, size, storage efficiency, export policies, and other attributes. To use this resource, you must create the Link module. Once activated, you will need a preview key to consume this resource. Please reach out to Ng-fsx-cloudformation@netapp.com to
Home-page: https://github.com/NetApp/NetApp-CloudFormation-FSx-ONTAP-provider
Author: Amazon Web Services
License: Apache-2.0
Project-URL: Source, https://github.com/cdklabs/cdk-cloudformation.git
Classifier: Intended Audience :: Developers
Classifier: Operating System :: OS Independent
Classifier: Programming Language :: JavaScript
Classifier: Programming Language :: Python :: 3 :: Only
Classifier: Programming Language :: Python :: 3.8
Classifier: Programming Language :: Python :: 3.9
Classifier: Programming Language :: Python :: 3.10
Classifier: Programming Language :: Python :: 3.11
Classifier: Typing :: Typed
Classifier: License :: OSI Approved
Requires-Python: ~=3.8
License-File: LICENSE
Requires-Dist: aws-cdk-lib<3.0.0,>=2.177.0
Requires-Dist: constructs<11.0.0,>=10.4.2
Requires-Dist: jsii<2.0.0,>=1.106.0
Requires-Dist: publication>=0.0.3
Requires-Dist: typeguard<4.3.0,>=2.13.3
Dynamic: author
Dynamic: classifier
Dynamic: description
Dynamic: description-content-type
Dynamic: home-page
Dynamic: license
Dynamic: project-url
Dynamic: requires-dist
Dynamic: requires-python
Dynamic: summary
